copytool/README.md
copytool/__init__.py
copytool/buffercalc.cp310-win_amd64.pyd
copytool/buffercalc.pyx
copytool/requirements.txt
copytool/thirdparty.json
copytool/buffcall/__init__.py
copytool/buffcall/buffercalc.cp310-win_amd64.pyd
copytool-0.12.dist-info/LICENSE.rst
copytool-0.12.dist-info/METADATA
copytool-0.12.dist-info/WHEEL
copytool-0.12.dist-info/top_level.txt
copytool-0.12.dist-info/RECORD
