Metadata-Version: 2.1
Name: copytool
Version: 0.12
Summary: copytool copies files hell-bent for leather
Home-page: https://github.com/hansalemaos/copytool
Author: Johannes Fischer
Author-email: aulasparticularesdealemaosp@gmail.com
License: MIT
Keywords: copy
Classifier: Development Status :: 4 - Beta
Classifier: Programming Language :: Python :: 3 :: Only
Classifier: Programming Language :: Python :: 3.10
Classifier: Topic :: Software Development :: Libraries :: Python Modules
Classifier: Topic :: Utilities
License-File: LICENSE.rst
Requires-Dist: getfilenuitkapython
Requires-Dist: hackyargparser
Requires-Dist: pandas
Requires-Dist: touchtouch
Requires-Dist: tqdm
Requires-Dist: uffspd
